Metadata-Version: 1.1
Name: getready
Version: 0.1
Summary: Get Ready Forever !
Home-page: UNKNOWN
Author: Werner Van Geit
Author-email: werner.vangeit@gmail.com
License: LGPLv3
Platform: UNKNOWN
Classifier: Development Status :: 4 - Beta
